PySQIF/InductanceConstants.py
PySQIF/InputData.py
PySQIF/Main.py
PySQIF/Output.py
PySQIF/PhiExt.py
PySQIF/Plot.py
PySQIF/PySQIF.py
PySQIF/Solver.py
PySQIF/TimeStep.py
PySQIF/Voltage.py
PySQIF/YieldIc3.py
PySQIF/__init__.py
PySQIF/example.py
PySQIF-0.0.9.dist-info/LICENSE
PySQIF-0.0.9.dist-info/METADATA
PySQIF-0.0.9.dist-info/WHEEL
PySQIF-0.0.9.dist-info/top_level.txt
PySQIF-0.0.9.dist-info/RECORD
