Metadata-Version: 2.1
Name: PySQIF
Version: 0.0.9
Summary: Analysis library for Bi-SQUID circuits.
Home-page: https://github.com/aakgn/PySQIF
Author: ali akgun
Author-email: ali.akgunphys@gmail.com
License: UNKNOWN
Project-URL: Bug Tracker, https://github.com/aakgn/PySQIF/issues
Platform: UNKNOWN
Classifier: Programming Language :: Python :: 3
Classifier: License :: OSI Approved :: MIT License
Classifier: Operating System :: OS Independent
Requires-Python: >=3.6
License-File: LICENSE
